cloudoll/__init__.py
cloudoll/__main__.py
cloudoll/cli.py
cloudoll/clitool/__init__.py
cloudoll/clitool/cli_main.py
cloudoll/clitool/m2d.py
cloudoll/clitool/process.py
cloudoll/clitool/spinner.py
cloudoll/clitool/watch.py
cloudoll/logging/__init__.py
cloudoll/mail/__init__.py
cloudoll/mail/smtp.py
cloudoll/orm/__init__.py
cloudoll/orm/awsmysql.py
cloudoll/orm/awspostgres.py
cloudoll/orm/base.py
cloudoll/orm/err.py
cloudoll/orm/field.py
cloudoll/orm/model.py
cloudoll/orm/mysql.py
cloudoll/orm/parse.py
cloudoll/orm/postgres.py
cloudoll/orm/test_sql.py
cloudoll/template/__init__.py
cloudoll/utils/__init__.py
cloudoll/utils/common.py
cloudoll/utils/password.py
cloudoll/utils/snowflake.py
cloudoll/web/__init__.py
cloudoll/web/core.py
cloudoll/web/exception.py
cloudoll/web/html.py
cloudoll/web/jwt.py
cloudoll/web/requests.py
cloudoll/web/settings.py
cloudoll-3.0.13.dist-info/licenses/LICENSE
cloudoll-3.0.13.dist-info/METADATA
cloudoll-3.0.13.dist-info/WHEEL
cloudoll-3.0.13.dist-info/entry_points.txt
cloudoll-3.0.13.dist-info/top_level.txt
cloudoll-3.0.13.dist-info/RECORD
