Metadata-Version: 2.4
Name: cloudoll
Version: 3.0.13
Summary: Assist in quickly creating distributable microservices based on aiohttp, with a focus on simplicity and ease of use.
Home-page: https://github.com/smallerqiu/cloudoll-py
Author: Qiu
Author-email: Qiu <smallerqiu@gmail.com>
License-Expression: MIT
Project-URL: Homepage, https://github.com/smallerqiu/cloudoll-py
Project-URL: Repository, https://github.com/smallerqiu/cloudoll-py
Keywords: Microservices,aiohttp,cloudoll
Classifier: Programming Language :: Python :: 3
Classifier: Programming Language :: Python :: 3.6
Classifier: Programming Language :: Python :: Implementation :: CPython
Classifier: Programming Language :: Python :: Implementation :: PyPy
Requires-Python: >=3.6.0
License-File: LICENSE
Requires-Dist: watchfiles
Requires-Dist: colorlog
Requires-Dist: aiomysql
Requires-Dist: aiopg
Requires-Dist: aiohttp
Requires-Dist: redis[hiredis]
Requires-Dist: aiomcache
Requires-Dist: jinja2
Requires-Dist: pyjwt
Requires-Dist: aiohttp_session[secure]
Requires-Dist: PyYAML
Requires-Dist: click
Requires-Dist: envyaml
Requires-Dist: psutil
Requires-Dist: tabulate
Requires-Dist: concurrent_log_handler
Dynamic: license-file
